detect_and_click/__init__.py
detect_and_click/cli.py
detect_and_click/clicker.py
detect_and_click/detector.py
detect_and_click-0.2.0.dist-info/METADATA
detect_and_click-0.2.0.dist-info/WHEEL
detect_and_click-0.2.0.dist-info/top_level.txt
detect_and_click-0.2.0.dist-info/RECORD
