Metadata-Version: 2.4
Name: detect-and-click
Version: 0.2.0
Summary: Библиотека для детекции объектов на экране и автоматического клика по ним
Author: Alex
License: MIT
Classifier: Programming Language :: Python :: 3
Classifier: License :: OSI Approved :: MIT License
Classifier: Operating System :: OS Independent
Requires-Python: >=3.7
Requires-Dist: opencv-python
Requires-Dist: mss
Requires-Dist: numpy
Requires-Dist: ultralytics
Requires-Dist: pyautogui
Provides-Extra: dev
Requires-Dist: pytest; extra == "dev"
Requires-Dist: flake8; extra == "dev"
Requires-Dist: mypy; extra == "dev"
